{"/":{"id":"","path":"/","title":"","type":"folder","children":["Getting-Started","Concepts","Guides","Reference"]},"Concepts":{"id":"folder-Concepts","title":"Concepts","children":["Concepts/What-is-Contour.md"],"type":"folder","path":"Concepts"},"Getting-Started":{"id":"folder-Getting-Started","title":"Getting-Started","children":["Getting-Started/QuickStart.md"],"type":"folder","path":"Getting-Started"},"Guides":{"id":"folder-Guides","title":"Guides","children":["Guides/Transactions.md"],"type":"folder","path":"Guides"},"Reference":{"id":"folder-Reference","title":"Reference","children":["Reference/System-Requirements.md"],"type":"folder","path":"Reference"},"Guides/Transactions.md":{"id":"Transactions","title":"Transactions","type":"document","path":"Guides/Transactions.md"},"Reference/System-Requirements.md":{"id":"System-Requirements","title":"System Requirements","type":"document","path":"Reference/System-Requirements.md"},"Concepts/What-is-Contour.md":{"id":"id-What-is-Contour","path":"Concepts/What-is-Contour.md","type":"document","title":"What is Prisma"},"Getting-Started/QuickStart.md":{"id":"id-QuickStart","path":"Getting-Started/QuickStart.md","type":"document","title":"QuickStart"}}